Metadata-Version: 2.1
Name: mediatr
Version: 1.1.2.3
Summary: mediator and CQRS pattern implementation with pipline behaviors for Python 3.5+. Mediatr py
Home-page: https://github.com/megafetis/mediatr_py
Author: Evgeniy Fetisov
Author-email: me@efetisov.ru
License: MIT -or- Apache License 2.0
Keywords: mediator,mediatr,CQRS,cqrs,mediatr_py,mediator py,mediatr py,pipline,behaviors,command,query,responsability,segregation,command bus,bus
Platform: UNKNOWN
Classifier: Development Status :: 5 - Production/Stable
Classifier: Intended Audience :: Developers
Classifier: Topic :: Software Development :: Build Tools
Classifier: License :: OSI Approved :: MIT License
Classifier: License :: OSI Approved :: Apache Software License
Classifier: Programming Language :: Python :: Implementation :: CPython
Classifier: Programming Language :: Python :: Implementation :: PyPy
Classifier: Programming Language :: Python :: 3 :: Only
Classifier: Programming Language :: Python :: 3.5
Classifier: Programming Language :: Python :: 3.6
Classifier: Programming Language :: Python :: 3.7
Classifier: Programming Language :: Python :: 3.9
Requires-Python: >=3.5
